__init__.py
Iodeum/__init__.py
Iodeum/main.py
pydeum-0.0.2.dist-info/LICENSE
pydeum-0.0.2.dist-info/METADATA
pydeum-0.0.2.dist-info/WHEEL
pydeum-0.0.2.dist-info/top_level.txt
pydeum-0.0.2.dist-info/RECORD
